Metadata-Version: 2.1
Name: shaderpy
Version: 0.0.4
Summary: A simple shader package for Pyglet.
Home-page: UNKNOWN
Author: Samuel Karabetian
License: MIT
Keywords: opengl,shader
Platform: UNKNOWN
Classifier: Development Status :: 2 - Pre-Alpha
Classifier: Intended Audience :: Developers
Classifier: Operating System :: Microsoft :: Windows :: Windows 10
Classifier: License :: OSI Approved :: MIT License
Classifier: Programming Language :: Python :: 3
